nonebot_plugin_writer/__init__.py
nonebot_plugin_writer/config.py
nonebot_plugin_writer/limiter.py
nonebot_plugin_writer/writer.py
nonebot_plugin_writer-0.2.0.dist-info/LICENSE
nonebot_plugin_writer-0.2.0.dist-info/METADATA
nonebot_plugin_writer-0.2.0.dist-info/WHEEL
nonebot_plugin_writer-0.2.0.dist-info/top_level.txt
nonebot_plugin_writer-0.2.0.dist-info/RECORD
