Metadata-Version: 2.1
Name: nonebot-plugin-writer
Version: 0.2.0
Summary: 基于 百度文心大模型 的 NoneBot2 promote索引文字生成插件
Home-page: https://github.com/ANGJustinl/nonebot_plugin_writer
Author: ANGJustinl
Author-email: angjustin@126.com
License: UNKNOWN
Keywords: pip,nonebot2,nonebot,nonebot_plugin
Platform: any
Classifier: Programming Language :: Python :: 3
Classifier: Operating System :: OS Independent
Requires-Python: >=3.7.3
License-File: LICENSE
Requires-Dist: httpx (==0.23.0nonebot==1.9.1nb-cli>=0.6.7nonebot-plugin-apscheduler>=0.2.0nonebot-adapter-onebot>=2.1.4nonebot-plugin-apscheduler>=0.2.0nonebot-plugin-autohelp>=0.1.7nonebot-plugin-datastore>=0.4.0nonebot-plugin-heweather>=0.6.0nonebot-plugin-htmlrender>=0.1.1nonebot-plugin-localstore>=0.2.0pydantic==1.9.2setuptools==57.4.0wenxin_api==0.0.5.1toml>=0.10.2yarl>=1.8.1poetry>=1.2.2poetry-core>=1.3.2poetry-plugin-export>=1.1.2)
